{
  "model": "meta-llama/Llama-3.1-8B-Instruct",
  "timestamp": "2026-01-09T18:16:24.093469Z",
  "num_samples": 50,
  "prompt_level_accuracy": 76.0,
  "prompt_level_accuracy_loose": 80.0,
  "instruction_level_accuracy": 81.57894736842105,
  "instruction_level_accuracy_loose": 84.21052631578947,
  "raw_report": {
    "eval_results_strict": "{'prompt_accuracy': 0.76, 'instruction_accuracy': 0.8157894736842105, 'category_accuracy': {'change_case': 0.7, 'combination': 0.8333333333333334, 'detectable_content': 1.0, 'detectable_format': 0.7142857142857143, 'keywords': 0.8125, 'language': 0.5, 'length_constraints': 1.0, 'punctuation': 1.0, 'startend': 0.7142857142857143}, 'instruction_accuracy_by_type': {'change_case:capital_word_frequency': 0.5, 'change_case:english_capital': 0.6666666666666666, 'change_case:english_lowercase': 0.8, 'combination:repeat_prompt': 0.6666666666666666, 'combination:two_responses': 1.0, 'detectable_content:number_placeholders': 1.0, 'detectable_content:postscript': 1.0, 'detectable_format:json_format': 0.6, 'detectable_format:multiple_sections': 1.0, 'detectable_format:number_bullet_lists': 0.0, 'detectable_format:number_highlighted_sections': 0.6666666666666666, 'detectable_format:title': 1.0, 'keywords:existence': 1.0, 'keywords:forbidden_words': 1.0, 'keywords:frequency': 0.8, 'keywords:letter_frequency': 0.5, 'language:response_language': 0.5, 'length_constraints:number_paragraphs': 1.0, 'length_constraints:number_sentences': 1.0, 'length_constraints:number_words': 1.0, 'punctuation:no_comma': 1.0, 'startend:end_checker': 0.5, 'startend:quotation': 1.0}, 'prompt_total': 50, 'prompt_correct': 38, 'instruction_total': 76, 'instruction_correct': 62}",
    "eval_results_loose": "{'prompt_accuracy': 0.8, 'instruction_accuracy': 0.8421052631578947, 'category_accuracy': {'change_case': 0.8, 'combination': 0.8333333333333334, 'detectable_content': 1.0, 'detectable_format': 0.7857142857142857, 'keywords': 0.8125, 'language': 0.5, 'length_constraints': 1.0, 'punctuation': 1.0, 'startend': 0.7142857142857143}, 'instruction_accuracy_by_type': {'change_case:capital_word_frequency': 0.5, 'change_case:english_capital': 0.6666666666666666, 'change_case:english_lowercase': 1.0, 'combination:repeat_prompt': 0.6666666666666666, 'combination:two_responses': 1.0, 'detectable_content:number_placeholders': 1.0, 'detectable_content:postscript': 1.0, 'detectable_format:json_format': 0.8, 'detectable_format:multiple_sections': 1.0, 'detectable_format:number_bullet_lists': 0.0, 'detectable_format:number_highlighted_sections': 0.6666666666666666, 'detectable_format:title': 1.0, 'keywords:existence': 1.0, 'keywords:forbidden_words': 1.0, 'keywords:frequency': 0.8, 'keywords:letter_frequency': 0.5, 'language:response_language': 0.5, 'length_constraints:number_paragraphs': 1.0, 'length_constraints:number_sentences': 1.0, 'length_constraints:number_words': 1.0, 'punctuation:no_comma': 1.0, 'startend:end_checker': 0.5, 'startend:quotation': 1.0}, 'prompt_total': 50, 'prompt_correct': 40, 'instruction_total': 76, 'instruction_correct': 64}"
  }
}